Workbook

Sheet Assumptions
A1: DCF Assumptions — Costco Wholesale Corporation (COST)
A3: Base Revenue ($) | B3: 254453000000 | C3: FY2024 actual, Source: 10-K FY2024, EDGAR accession 0000909832-24-000031
A4: Year 1 Growth Rate | B4: 0.07 | C4: Analyst estimate — edit this cell to test sensitivity
A5: Year 2 Growth Rate | B5: 0.065 | C5: Analyst estimate
A6: Year 3 Growth Rate | B6: 0.06 | C6: Analyst estimate
A7: Year 4 Growth Rate | B7: 0.055 | C7: Analyst estimate
A8: Year 5 Growth Rate | B8: 0.05 | C8: Analyst estimate
A9: EBIT Margin | B9: 0.036490039 | C9: FY2024 actual operating income / revenue (exact, matches Python engine)
A10: Tax Rate | B10: 0.25 | C10: Approximate blended statutory rate
A11: CapEx % of Revenue | B11: 0.018 | C11: Analyst estimate based on historical capex/revenue
A12: D&A % of Revenue | B12: 0.012 | C12: Analyst estimate
A13: NWC Change % of Revenue Change | B13: 0.01 | C13: Analyst estimate
A14: WACC | B14: 0.08 | C14: Key assumption — highly sensitive, see Sensitivity tab
... A18: Current Share Price ($) | B18: 920 | C18: Illustrative — replace with live market price

Sheet DCF Model
A1: DCF Model — Free Cash Flow Projection
A3: Line Item | B3: Year 1 | C3: Year 2 | D3: Year 3 | E3: Year 4 | F3: Year 5
A4: Revenue | B4: =Assumptions!$B$3*(1+Assumptions!$B$4) -> 272264710000 | C4: =B4*(1+Assumptions!$B$5) -> 289961916150 | D4: =C4*(1+Assumptions!$B$6) -> 307359631119 | E4: =D4*(1+Assumptions!$B$7) -> 3.2426441e+11 | F4: =E4*(1+Assumptions!$B$8) -> 3.4047763e+11
A5: EBIT | B5: =B4*Assumptions!$B$9 -> 9934950000 | C5: =C4*Assumptions!$B$9 -> 10580721750 | D5: =D4*Assumptions!$B$9 -> 11215565055 | E5: =E4*Assumptions!$B$9 -> 1.1832421e+10 | F5: =F4*Assumptions!$B$9 -> 1.2424042e+10
A6: NOPAT | B6: =B5*(1-Assumptions!$B$10) -> 7451212500 | C6: =C5*(1-Assumptions!$B$10) -> 7.9355413e+09 | D6: =D5*(1-Assumptions!$B$10) -> 8.4116738e+09 | E6: =E5*(1-Assumptions!$B$10) -> 8.8743158e+09 | F6: =F5*(1-Assumptions!$B$10) -> 9.3180316e+09
A7: CapEx | B7: =B4*Assumptions!$B$11 -> 4900764780 | C7: =C4*Assumptions!$B$11 -> 5.2193145e+09 | D7: =D4*Assumptions!$B$11 -> 5.5324734e+09 | E7: =E4*Assumptions!$B$11 -> 5.8367594e+09 | F7: =F4*Assumptions!$B$11 -> 6.1285974e+09
A8: D&A | B8: =B4*Assumptions!$B$12 -> 3267176520 | C8: =C4*Assumptions!$B$12 -> 3.479543e+09 | D8: =D4*Assumptions!$B$12 -> 3.6883156e+09 | E8: =E4*Assumptions!$B$12 -> 3.8911729e+09 | F8: =F4*Assumptions!$B$12 -> 4.0857316e+09
A9: Change in NWC | B9: =(B4-Assumptions!$B$3)*Assumptions!$B$13 -> 178117100 | C9: =(C4-B4)*Assumptions!$B$13 -> 1.7697206e+08 | D9: =(D4-C4)*Assumptions!$B$13 -> 1.7397715e+08 | E9: =(E4-D4)*Assumptions!$B$13 -> 1.690478e+08 | F9: =(F4-E4)*Assumptions!$B$13 -> 1.6213221e+08
A10: Free Cash Flow | B10: =B6+B8-B7-B9 -> 5639507140 | C10: =C6+C8-C7-C9 -> 6.0187978e+09 | D10: =D6+D8-D7-D9 -> 6.3935389e+09 | E10: =E6+E8-E7-E9 -> 6.7596816e+09 | F10: =F6+F8-F7-F9 -> 7.1130336e+09
A11: Discount Factor | B11: =1/(1+Assumptions!$B$14)^1 -> 0.92592593 | C11: =1/(1+Assumptions!$B$14)^2 -> 0.85733882 | D11: =1/(1+Assumptions!$B$14)^3 -> 0.79383224 | E11: =1/(1+Assumptions!$B$14)^4 -> 0.73502985 | F11: =1/(1+Assumptions!$B$14)^5 -> 0.6805832
A12: Present Value of FCF | B12: =B10*B11 -> 5.2217659e+09 | C12: =C10*C11 -> 5.160149e+09 | D12: =D10*D11 -> 5.0753973e+09 | E12: =E10*E11 -> 4.9685678e+09 | F12: =F10*F11 -> 4.8410112e+09
A14: Valuation Bridge
A15: Sum of PV of FCF (Years 1-5) | B15: =SUM(B12:F12) -> 2.5266891e+10
A16: Terminal Value (Gordon Growth) | B16: =F10*(1+Assumptions!$B$15)/(Assumptions!$B$14-Assumptions!$B$15) -> 1.3256108e+11
A17: PV of Terminal Value | B17: =B16*F11 -> 9.0218845e+10
A18: Enterprise Value | B18: =B15+B17 -> 1.1548574e+11
A19: Equity Value | B19: =B18-Assumptions!$B$16 -> 1.2548574e+11
A20: Implied Share Price | B20: =B19/Assumptions!$B$17 -> 283.26351
A22: Upside / (Downside) vs. Current Price | B22: =(B20-Assumptions!$B$18)/Assumptions!$B$18 -> -0.69210488

Sheet Financials
A1: Historical Financials — COST ($, FY basis)
A3: Line Item | B3: FY2022 | C3: FY2023 | D3: FY2024
A4: Revenue | B4: 226954000000 | C4: 242290000000 | D4: 254453000000
A5: Cost of Goods Sold | B5: 201402000000 | C5: 215214000000 | D5: 225954000000
A6: Operating Income | B6: 7793000000 | C6: 8114000000 | D6: 9285000000
A7: Net Income | B7: 5844000000 | C7: 6292000000 | D7: 7367000000
A8: Stockholders Equity | B8: 20642000000 | C8: 22931000000 | D8: 26490000000
A9: Current Assets | B9: 30664000000 | C9: 32351000000 | D9: 34326000000
A10: Current Liabilities | B10: 30413000000 | C10: 32991000000 | D10: 34549000000
A11: Operating Cash Flow | B11: 7385000000 | C11: 9741000000 | D11: 11269000000
A12: CapEx | B12: 3891000000 | C12: 4078000000 | D12: 4710000000
A13: Source: SEC EDGAR 10-K filings FY2022-FY2024 (XBRL); see README for accession numbers

Sheet Ratios
A1: Financial Ratios (formula-driven from Financials tab)
A3: Ratio | B3: FY2022 | C3: FY2023 | D3: FY2024
A4: Gross Margin | B4: =(Financials!B4-Financials!B5)/Financials!B4 -> 0.11258669 | C4: =(Financials!C4-Financials!C5)/Financials!C4 -> 0.11175038 | D4: =(Financials!D4-Financials!D5)/Financials!D4 -> 0.11200104
A5: Operating Margin | B5: =Financials!B6/Financials!B4 -> 0.034337355 | C5: =Financials!C6/Financials!C4 -> 0.033488794 | D5: =Financials!D6/Financials!D4 -> 0.036490039
A6: Net Margin | B6: =Financials!B7/Financials!B4 -> 0.025749711 | C6: =Financials!C7/Financials!C4 -> 0.02596888 | D6: =Financials!D7/Financials!D4 -> 0.028952302
A7: ROE | B7: =Financials!B7/Financials!B8 -> 0.2831121 | C7: =Financials!C7/Financials!C8 -> 0.27438838 | D7: =Financials!D7/Financials!D8 -> 0.27810495
A8: Current Ratio | B8: =Financials!B9/Financials!B10 -> 1.008253 | C8: =Financials!C9/Financials!C10 -> 0.98060077 | D8: =Financials!D9/Financials!D10 -> 0.9935454
A9: FCF Margin | B9: =(Financials!B11-Financials!B12)/Financials!B4 -> 0.01539519 | C9: =(Financials!C11-Financials!C12)/Financials!C4 -> 0.023372818 | D9: =(Financials!D11-Financials!D12)/Financials!D4 -> 0.025776863
A10: Revenue Growth YoY | B10: n/a (no prior year) | C10: =(Financials!C4-Financials!B4)/Financials!B4 -> 0.067573165 | D10: =(Financials!D4-Financials!C4)/Financials!C4 -> 0.050200173

Sheet Comps
A1: Comparable Companies
A3: Ticker | B3: Company | C3: EV/EBITDA | D3: P/E | E3: EV/Revenue | F3: Rev Growth | G3: Op Margin
A4: WMT | B4: Walmart Inc. | C4: 15.2 | D4: 28.4 | E4: 1.1 | F4: 0.056 | G4: 0.044
A5: TGT | B5: Target Corp. | C5: 8.1 | D5: 16.3 | E5: 0.6 | F5: 0.021 | G5: 0.055
A6: BJ | B6: BJ's Wholesale Club | C6: 11.4 | D6: 19.8 | E6: 0.7 | F6: 0.041 | G6: 0.033
A7: DG | B7: Dollar General Corp. | C7: 9.7 | D7: 17.5 | E7: 0.9 | F7: 0.032 | G7: 0.049
B9: Peer Median | C9: =MEDIAN(C4:C7) -> 10.55 | D9: =MEDIAN(D4:D7) -> 18.65 | E9: =MEDIAN(E4:E7) -> 0.8 | F9: =MEDIAN(F4:F7) -> 0.0365 | G9: =MEDIAN(G4:G7) -> 0.0465
A11: Implied share price (DCF, for reference): | C11: ='DCF Model'!$B$20 -> 283.26351
